<?xml version = '1.0' encoding = 'UTF-8'?>
<hwTaskFlows xmlns="http://xmlns.oracle.com/bpel/workflow/hwTaskFlowProperties">
   <ApplicationName>worklist</ApplicationName>
   <LookupType>LOCAL</LookupType>
   <TaskFlowDeploy>false</TaskFlowDeploy>
   <TaskFlowServer>
      <hostName/>
      <httpPort/>
      <httpsPort/>
   </TaskFlowServer>
<hwTaskFlow><WorkflowName>Manager_Human</WorkflowName><TaskDefinitionNamespace>http://xmlns.oracle.com/Capstone1/Approvl/Manager_Human</TaskDefinitionNamespace><TaskFlowId>Manager_Human_TaskFlow</TaskFlowId><TaskFlowFileName>WEB-INF/Manager_Human_TaskFlow.xml</TaskFlowFileName></hwTaskFlow></hwTaskFlows>
